MANIFEST.in
setup.py
grr_response_test/__init__.py
grr_response_test/api_regression_test_generate.py
grr_response_test/distro_entry.py
grr_response_test/dump_mysql_schema.py
grr_response_test/run_end_to_end_tests.py
grr_response_test/run_kill_fleetspeak_tests.py
grr_response_test/run_self_contained.py
grr_response_test.egg-info/PKG-INFO
grr_response_test.egg-info/SOURCES.txt
grr_response_test.egg-info/dependency_links.txt
grr_response_test.egg-info/entry_points.txt
grr_response_test.egg-info/requires.txt
grr_response_test.egg-info/top_level.txt
grr_response_test/end_to_end_tests/__init__.py
grr_response_test/end_to_end_tests/fake_tests.py
grr_response_test/end_to_end_tests/runner.py
grr_response_test/end_to_end_tests/runner_test.py
grr_response_test/end_to_end_tests/test_base.py
grr_response_test/end_to_end_tests/tests/__init__.py
grr_response_test/end_to_end_tests/tests/administrative.py
grr_response_test/end_to_end_tests/tests/artifacts.py
grr_response_test/end_to_end_tests/tests/containers.py
grr_response_test/end_to_end_tests/tests/discovery.py
grr_response_test/end_to_end_tests/tests/dummy.py
grr_response_test/end_to_end_tests/tests/file_finder.py
grr_response_test/end_to_end_tests/tests/filesystem.py
grr_response_test/end_to_end_tests/tests/large_file.py
grr_response_test/end_to_end_tests/tests/limits.py
grr_response_test/end_to_end_tests/tests/memory.py
grr_response_test/end_to_end_tests/tests/network.py
grr_response_test/end_to_end_tests/tests/osquery.py
grr_response_test/end_to_end_tests/tests/processes.py
grr_response_test/end_to_end_tests/tests/registry.py
grr_response_test/end_to_end_tests/tests/timeline.py
grr_response_test/end_to_end_tests/tests/transfer.py
grr_response_test/lib/__init__.py
grr_response_test/lib/api_helpers.py
grr_response_test/lib/self_contained_components.py
grr_response_test/lib/self_contained_config_writer.py
grr_response_test/test_data/History.plist
grr_response_test/test_data/History.xml.plist
grr_response_test/test_data/apache_false_log
grr_response_test/test_data/apache_log
grr_response_test/test_data/approvers.yaml
grr_response_test/test_data/blank.yaml
grr_response_test/test_data/client_certs
grr_response_test/test_data/dmesg
grr_response_test/test_data/dmidecode.out
