Metadata-Version: 2.4
Name: grr-response-test
Version: 4.0.0.post0
Summary: The GRR Rapid Response test suite.
Home-page: https://github.com/google/grr
License: Apache License, Version 2.0
Requires-Dist: absl-py==1.4.0
Requires-Dist: flaky==3.7.0
Requires-Dist: pytest==7.2.1
Requires-Dist: responses==0.22.0
Requires-Dist: selenium==3.141.0
Requires-Dist: google-api-python-client==1.12.11
Requires-Dist: grr-api-client==4.0.0post0
Requires-Dist: grr-response-client==4.0.0post0
Requires-Dist: grr-response-server==4.0.0post0
Dynamic: home-page
Dynamic: license
Dynamic: requires-dist
Dynamic: summary
